rest_framework_simplejwt/__init__.py
rest_framework_simplejwt/authentication.py
rest_framework_simplejwt/backends.py
rest_framework_simplejwt/compat.py
rest_framework_simplejwt/exceptions.py
rest_framework_simplejwt/models.py
rest_framework_simplejwt/serializers.py
rest_framework_simplejwt/settings.py
rest_framework_simplejwt/state.py
rest_framework_simplejwt/tokens.py
rest_framework_simplejwt/utils.py
rest_framework_simplejwt/views.py
rest_framework_simplejwt/locale/cs/LC_MESSAGES/django.mo
rest_framework_simplejwt/locale/cs/LC_MESSAGES/django.po
rest_framework_simplejwt/locale/de_CH/LC_MESSAGES/django.mo
rest_framework_simplejwt/locale/de_CH/LC_MESSAGES/django.po
rest_framework_simplejwt/locale/es_AR/LC_MESSAGES/django.mo
rest_framework_simplejwt/locale/es_AR/LC_MESSAGES/django.po
rest_framework_simplejwt/locale/es_CL/LC_MESSAGES/django.mo
rest_framework_simplejwt/locale/es_CL/LC_MESSAGES/django.po
rest_framework_simplejwt/locale/fa_IR/LC_MESSAGES/django.mo
rest_framework_simplejwt/locale/fa_IR/LC_MESSAGES/django.po
rest_framework_simplejwt/locale/pl_PL/LC_MESSAGES/django.mo
rest_framework_simplejwt/locale/pl_PL/LC_MESSAGES/django.po
rest_framework_simplejwt/locale/pt_BR/LC_MESSAGES/django.mo
rest_framework_simplejwt/locale/pt_BR/LC_MESSAGES/django.po
rest_framework_simplejwt/locale/ru_RU/LC_MESSAGES/django.mo
rest_framework_simplejwt/locale/ru_RU/LC_MESSAGES/django.po
rest_framework_simplejwt/token_blacklist/__init__.py
rest_framework_simplejwt/token_blacklist/admin.py
rest_framework_simplejwt/token_blacklist/apps.py
rest_framework_simplejwt/token_blacklist/models.py
rest_framework_simplejwt/token_blacklist/management/__init__.py
rest_framework_simplejwt/token_blacklist/management/commands/__init__.py
rest_framework_simplejwt/token_blacklist/management/commands/flushexpiredtokens.py
rest_framework_simplejwt/token_blacklist/migrations/0001_initial.py
rest_framework_simplejwt/token_blacklist/migrations/0002_outstandingtoken_jti_hex.py
cfjwt-4.4.0.dist-info/LICENSE.txt
cfjwt-4.4.0.dist-info/METADATA
cfjwt-4.4.0.dist-info/WHEEL
cfjwt-4.4.0.dist-info/top_level.txt
cfjwt-4.4.0.dist-info/RECORD
